physplotlib
